<?xml version="1.0" encoding="utf-8" ?>
<dwsync>
<file name="categories.html" server="192.168.16.254//var/www/php-dev/" local="130161256200000000" remote="130174534340000000" />
<file name="remote-jsonp.html" server="192.168.16.254//var/www/php-dev/" local="130161256200000000" remote="130174534350000000" />
<file name="custom-data.html" server="192.168.16.254//var/www/php-dev/" local="130161256200000000" remote="130174534360000000" />
<file name="default.html" server="192.168.16.254//var/www/php-dev/" local="130161256200000000" remote="130174534370000000" />
<file name="multiple-remote.html" server="192.168.16.254//var/www/php-dev/" local="130161256200000000" remote="130174534370000000" />
<file name="remote-with-cache.html" server="192.168.16.254//var/www/php-dev/" local="130161256200000000" remote="130174534380000000" />
<file name="london.xml" server="192.168.16.254//var/www/php-dev/" local="130161256200000000" remote="130174534380000000" />
<file name="remote.html" server="192.168.16.254//var/www/php-dev/" local="130161256200000000" remote="130174534380000000" />
<file name="combobox.html" server="192.168.16.254//var/www/php-dev/" local="130161256200000000" remote="130174534390000000" />
<file name="xml.html" server="192.168.16.254//var/www/php-dev/" local="130161256200000000" remote="130174534400000000" />
<file name="index.html" server="192.168.16.254//var/www/php-dev/" local="130161256200000000" remote="130174534400000000" />
<file name="maxheight.html" server="192.168.16.254//var/www/php-dev/" local="130161256200000000" remote="130174534440000000" />
<file name="search.php" server="192.168.16.254//var/www/php-dev/" local="130161256200000000" remote="130174534450000000" />
<file name="multiple.html" server="192.168.16.254//var/www/php-dev/" local="130161256200000000" remote="130174534450000000" />
<file name="folding.html" server="192.168.16.254//var/www/php-dev/" local="130161256200000000" remote="130174534450000000" />
</dwsync>